CHANGES.txt
LICENSE.txt
MANIFEST.in
README.rst
setup.py
ogr_cli/__init__.py
ogr_cli/ogr.py
ogrtools/__init__.py
ogrtools.egg-info/PKG-INFO
ogrtools.egg-info/SOURCES.txt
ogrtools.egg-info/dependency_links.txt
ogrtools.egg-info/entry_points.txt
ogrtools.egg-info/top_level.txt
ogrtools/interlis/__init__.py
ogrtools/interlis/ilismeta.py
ogrtools/interlis/java_exec.py
ogrtools/interlis/model_loader.py
ogrtools/ogrtransform/__init__.py
ogrtools/ogrtransform/format_handler.py
ogrtools/ogrtransform/ogrconfig.py
ogrtools/pyogr/__init__.py
ogrtools/pyogr/ogr2ogr.py
ogrtools/pyogr/ogrds.py
ogrtools/pyogr/ogrinfo.py
ogrtools/pyogr/ogrvrt.py
ogrtools/pyogr/singlegeomvrt.py