Metadata-Version: 1.1
Name: ogrtools
Version: 0.7.3
Summary: Collection of libraries and tools built with the Python API of OGR.
Home-page: https://github.com/sourcepole/ogrtools
Author: Pirmin Kalberer
Author-email: pka@sourcepole.ch
License: LICENSE.txt
Download-URL: https://github.com/sourcepole/mypackage/tarball/0.7.3
Platform: UNKNOWN
Classifier: Development Status :: 4 - Beta
Classifier: Intended Audience :: Developers
Classifier: Intended Audience :: Science/Research
Classifier: License :: OSI Approved :: MIT License
Classifier: Operating System :: OS Independent
Classifier: Programming Language :: Python :: 2
Classifier: Topic :: Scientific/Engineering :: GIS
